{
  "Nyarugenge": {
    "sectors": [
      [
        "Gitega",
        -1.9547,
        30.0574,
        "Clay loam"
      ],
      [
        "Kanyinya",
        -1.9425,
        30.0234,
        "Sandy clay"
      ],
      [
        "Kigali",
        -1.9494,
        30.0588,
        "Clay"
      ],
      [
        "Kimisagara",
        -1.9569,
        30.0397,
        "Sandy loam"
      ],
      [
        "Mageragere",
        -1.9872,
        30.0089,
        "Clay loam"
      ],
      [
        "Muhima",
        -1.9436,
        30.0614,
        "Sandy clay"
      ],
      [
        "Nyakabanda",
        -1.9647,
        30.0397,
        "Clay"
      ],
      [
        "Nyamirambo",
        -1.975,
        30.0397,
        "Sandy loam"
      ],
      [
        "Nyarugenge",
        -1.9508,
        30.0556,
        "Clay loam"
      ],
      [
        "Rwezamenyo",
        -1.9494,
        30.0556,
        "Clay"
      ]
    ]
  },
  "Gasabo": {
    "sectors": [
      [
        "Bumbogo",
        -1.8897,
        30.1147,
        "Sandy clay"
      ],
      [
        "Gatsata",
        -1.9178,
        30.0672,
        "Clay loam"
      ],
      [
        "Gikomero",
        -1.8794,
        30.1969,
        "Sandy loam"
      ],
      [
        "Gisozi",
        -1.9289,
        30.0839,
        "Clay"
      ],
      [
        "Jabana",
        -1.8961,
        30.0506,
        "Sandy clay"
      ],
      [
        "Jali",
        -1.8897,
        30.1672,
        "Clay loam"
      ],
      [
        "Kacyiru",
        -1.9447,
        30.0922,
        "Loamy sand"
      ],
      [
        "Kimihurura",
        -1.9536,
        30.0922,
        "Clay"
      ],
      [
        "Kimironko",
        -1.9494,
        30.1191,
        "Sandy loam"
      ],
      [
        "Kinyinya",
        -1.9178,
        30.1017,
        "Clay loam"
      ],
      [
        "Ndera",
        -1.9178,
        30.1672,
        "Sandy clay"
      ],
      [
        "Nduba",
        -1.8794,
        30.1372,
        "Clay"
      ],
      [
        "Remera",
        -1.9557,
        30.1097,
        "Clay loam"
      ],
      [
        "Rusororo",
        -1.9289,
        30.1447,
        "Sandy loam"
      ],
      [
        "Rutunga",
        -1.8897,
        30.1447,
        "Clay"
      ]
    ]
  },
  "Kicukiro": {
    "sectors": [
      [
        "Gahanga",
        -2.0247,
        30.1017,
        "Sandy clay"
      ],
      [
        "Gatenga",
        -1.9872,
        30.0922,
        "Clay loam"
      ],
      [
        "Gikondo",
        -1.975,
        30.0756,
        "Sandy loam"
      ],
      [
        "Kagarama",
        -1.9935,
        30.0922,
        "Clay"
      ],
      [
        "Kanombe",
        -1.975,
        30.1286,
        "Sandy clay"
      ],
      [
        "Kigarama",
        -2.0006,
        30.1156,
        "Clay loam"
      ],
      [
        "Masaka",
        -2.0247,
        30.1447,
        "Sandy loam"
      ],
      [
        "Niboye",
        -1.9872,
        30.1097,
        "Clay"
      ],
      [
        "Nyarugunga",
        -1.9935,
        30.1286,
        "Sandy clay"
      ],
      [
        "Kicukiro",
        -1.97,
        30.1,
        "Loam"
      ]
    ]
  },
  "Bugesera": {
    "sectors": [
      [
        "Bugesera-Sector-1",
        -1.0887142484621508,
        30.33718727780395,
        "Sandy Clay"
      ],
      [
        "Bugesera-Sector-2",
        -1.7256697156963234,
        29.73624878099254,
        "Loamy Sand"
      ],
      [
        "Bugesera-Sector-3",
        -2.6954494980972408,
        30.61896990612736,
        "Silty Clay"
      ],
      [
        "Bugesera-Sector-4",
        -2.5428397277405064,
        30.166865793192592,
        "Sandy Clay"
      ],
      [
        "Bugesera-Sector-5",
        -1.0541622661084102,
        30.548129545680883,
        "Loam"
      ],
      [
        "Bugesera-Sector-6",
        -2.798598221486174,
        30.883644274511557,
        "Clay"
      ],
      [
        "Bugesera-Sector-7",
        -2.252363962672832,
        29.9019885064277,
        "Silty Clay"
      ],
      [
        "Bugesera-Sector-8",
        -2.7584876349254515,
        29.902026786542617,
        "Loamy Sand"
      ]
    ]
  },
  "Gatsibo": {
    "sectors": [
      [
        "Gatsibo-Sector-1",
        -2.088729575196734,
        30.745983618166967,
        "Loamy Sand"
      ],
      [
        "Gatsibo-Sector-2",
        -1.1406263769583898,
        28.985834254309033,
        "Loamy Sand"
      ],
      [
        "Gatsibo-Sector-3",
        -1.8624983319535173,
        30.81846125113363,
        "Sandy Clay"
      ],
      [
        "Gatsibo-Sector-4",
        -2.100380878558932,
        29.36983296672518,
        "Sandy Clay"
      ],
      [
        "Gatsibo-Sector-5",
        -1.7438479018050732,
        30.827036145254688,
        "Silty Clay"
      ],
      [
        "Gatsibo-Sector-6",
        -1.8231470503151526,
        29.095940872447002,
        "Loamy Sand"
      ]
    ]
  },
  "Kayonza": {
    "sectors": [
      [
        "Kayonza-Sector-1",
        -1.3304226282051088,
        30.476524762467555,
        "Clay"
      ],
      [
        "Kayonza-Sector-2",
        -2.222595883050875,
        29.191688871839695,
        "Sandy Clay"
      ],
      [
        "Kayonza-Sector-3",
        -1.2549541513353042,
        29.48451370092396,
        "Silty Clay"
      ],
      [
        "Kayonza-Sector-4",
        -2.7701419079298586,
        29.87539542242849,
        "Sandy Loam"
      ],
      [
        "Kayonza-Sector-5",
        -2.1724012228748872,
        29.001970757291986,
        "Clay"
      ],
      [
        "Kayonza-Sector-6",
        -1.5563120714155612,
        29.612144227231127,
        "Clay Loam"
      ],
      [
        "Kayonza-Sector-7",
        -1.2921218093668096,
        30.21894924578249,
        "Clay"
      ]
    ]
  },
  "Kirehe": {
    "sectors": [
      [
        "Kirehe-Sector-1",
        -2.423671082672115,
        29.937040745037887,
        "Clay Loam"
      ],
      [
        "Kirehe-Sector-2",
        -2.33570507011272,
        30.185966496671774,
        "Clay Loam"
      ],
      [
        "Kirehe-Sector-3",
        -1.0320969820070158,
        29.88493537166913,
        "Clay"
      ],
      [
        "Kirehe-Sector-4",
        -2.364665876379187,
        28.995515812392387,
        "Silty Clay"
      ],
      [
        "Kirehe-Sector-5",
        -1.7950717835072243,
        30.65353632069761,
        "Loamy Sand"
      ]
    ]
  },
  "Ngoma": {
    "sectors": [
      [
        "Ngoma-Sector-1",
        -1.738232474391021,
        30.855675002377517,
        "Sandy Loam"
      ],
      [
        "Ngoma-Sector-2",
        -1.194316200681196,
        30.12539111459425,
        "Clay Loam"
      ],
      [
        "Ngoma-Sector-3",
        -2.1698588661495837,
        30.154717060264186,
        "Loamy Sand"
      ],
      [
        "Ngoma-Sector-4",
        -1.913468151126045,
        29.210010274375893,
        "Sandy Clay"
      ],
      [
        "Ngoma-Sector-5",
        -1.9014519162074457,
        30.001208818339283,
        "Volcanic Soil"
      ],
      [
        "Ngoma-Sector-6",
        -1.6381498673670978,
        29.171932426754804,
        "Silty Clay"
      ],
      [
        "Ngoma-Sector-7",
        -1.9540998748163028,
        29.387076717773194,
        "Loam"
      ],
      [
        "Ngoma-Sector-8",
        -2.1337143395402,
        28.832458894710623,
        "Volcanic Soil"
      ],
      [
        "Ngoma-Sector-9",
        -2.2046494515930752,
        29.960806430354527,
        "Loamy Sand"
      ],
      [
        "Ngoma-Sector-10",
        -1.065484041239345,
        30.591319856481455,
        "Loamy Sand"
      ]
    ]
  },
  "Nyagatare": {
    "sectors": [
      [
        "Nyagatare-Sector-1",
        -2.212027764767126,
        30.538524907953935,
        "Silty Clay"
      ],
      [
        "Nyagatare-Sector-2",
        -2.4115221505056823,
        30.1080699992199,
        "Silty Clay"
      ],
      [
        "Nyagatare-Sector-3",
        -1.2843584649784334,
        29.208198071389234,
        "Loam"
      ],
      [
        "Nyagatare-Sector-4",
        -1.8268567811018082,
        30.138602793146234,
        "Silty Clay"
      ],
      [
        "Nyagatare-Sector-5",
        -2.5610582399626542,
        30.836027420939732,
        "Clay Loam"
      ],
      [
        "Nyagatare-Sector-6",
        -2.2186783487057573,
        30.469891009014276,
        "Loamy Sand"
      ],
      [
        "Nyagatare-Sector-7",
        -2.0196626723546642,
        30.362489550298143,
        "Clay Loam"
      ],
      [
        "Nyagatare-Sector-8",
        -2.754368661852176,
        30.82156167082364,
        "Loamy Sand"
      ]
    ]
  },
  "Rwamagana": {
    "sectors": [
      [
        "Rwamagana-Sector-1",
        -1.547652359827689,
        29.754536236012324,
        "Sandy Clay"
      ],
      [
        "Rwamagana-Sector-2",
        -1.5455348994451332,
        29.60682384589636,
        "Loamy Sand"
      ],
      [
        "Rwamagana-Sector-3",
        -2.7181965153853755,
        29.390022698143685,
        "Volcanic Soil"
      ],
      [
        "Rwamagana-Sector-4",
        -2.6958449840361265,
        29.628495777077074,
        "Volcanic Soil"
      ],
      [
        "Rwamagana-Sector-5",
        -1.6837613239572338,
        29.38250048426038,
        "Silty Clay"
      ]
    ]
  },
  "Burera": {
    "sectors": [
      [
        "Burera-Sector-1",
        -2.716001806215492,
        30.844886589567064,
        "Loamy Sand"
      ],
      [
        "Burera-Sector-2",
        -1.979074028409335,
        30.448869518925328,
        "Sandy Loam"
      ],
      [
        "Burera-Sector-3",
        -2.111568415719107,
        30.864784860194256,
        "Clay"
      ],
      [
        "Burera-Sector-4",
        -2.716389257104004,
        30.07584418899302,
        "Sandy Clay"
      ],
      [
        "Burera-Sector-5",
        -1.9891013464548224,
        28.82785641843572,
        "Clay"
      ],
      [
        "Burera-Sector-6",
        -1.0618623404657932,
        30.497634431044567,
        "Clay"
      ]
    ]
  },
  "Gakenke": {
    "sectors": [
      [
        "Gakenke-Sector-1",
        -2.624190194788509,
        30.23688935567553,
        "Loamy Sand"
      ],
      [
        "Gakenke-Sector-2",
        -1.5701256661141751,
        30.080992981343503,
        "Volcanic Soil"
      ],
      [
        "Gakenke-Sector-3",
        -2.7381006619926067,
        30.70957284436544,
        "Silty Clay"
      ],
      [
        "Gakenke-Sector-4",
        -2.4719750419814877,
        30.386258961667068,
        "Loam"
      ],
      [
        "Gakenke-Sector-5",
        -1.8638775618799404,
        29.948091586620887,
        "Loam"
      ],
      [
        "Gakenke-Sector-6",
        -2.7436360735799945,
        30.568798026649496,
        "Silty Clay"
      ]
    ]
  },
  "Gicumbi": {
    "sectors": [
      [
        "Gicumbi-Sector-1",
        -2.6658088413764123,
        30.872462566861085,
        "Volcanic Soil"
      ],
      [
        "Gicumbi-Sector-2",
        -2.0892132672839745,
        29.416325166907882,
        "Loamy Sand"
      ],
      [
        "Gicumbi-Sector-3",
        -1.3321694287812984,
        30.284400422079994,
        "Sandy Loam"
      ],
      [
        "Gicumbi-Sector-4",
        -1.3776840270438298,
        30.072515947040124,
        "Clay Loam"
      ],
      [
        "Gicumbi-Sector-5",
        -2.154761688620309,
        29.043325025002773,
        "Loamy Sand"
      ],
      [
        "Gicumbi-Sector-6",
        -1.2699305599783612,
        29.74384641569023,
        "Clay"
      ],
      [
        "Gicumbi-Sector-7",
        -2.685594969485157,
        29.45306287560289,
        "Volcanic Soil"
      ],
      [
        "Gicumbi-Sector-8",
        -1.601339758088506,
        30.041725354186227,
        "Loam"
      ],
      [
        "Gicumbi-Sector-9",
        -1.2030170633626123,
        29.791651342840094,
        "Sandy Clay"
      ]
    ]
  },
  "Musanze": {
    "sectors": [
      [
        "Musanze-Sector-1",
        -1.047405093840429,
        29.396234046948678,
        "Loam"
      ],
      [
        "Musanze-Sector-2",
        -1.812279179140145,
        30.252979915154654,
        "Volcanic Soil"
      ],
      [
        "Musanze-Sector-3",
        -1.0099765673005228,
        29.169443030622425,
        "Silty Clay"
      ],
      [
        "Musanze-Sector-4",
        -2.3729516425057597,
        29.483339366134462,
        "Silty Clay"
      ],
      [
        "Musanze-Sector-5",
        -2.140356187750852,
        30.36275809841878,
        "Sandy Loam"
      ],
      [
        "Musanze-Sector-6",
        -1.616296793859382,
        29.99344806700449,
        "Silty Clay"
      ],
      [
        "Musanze-Sector-7",
        -1.884134661690232,
        30.136298498190378,
        "Loam"
      ]
    ]
  },
  "Rulindo": {
    "sectors": [
      [
        "Rulindo-Sector-1",
        -1.473335997776184,
        29.946423117346477,
        "Sandy Loam"
      ],
      [
        "Rulindo-Sector-2",
        -2.5892793704303094,
        29.100282532310956,
        "Clay Loam"
      ],
      [
        "Rulindo-Sector-3",
        -1.293465026372727,
        30.620424281152765,
        "Loam"
      ],
      [
        "Rulindo-Sector-4",
        -2.6486077489930047,
        30.27203517606415,
        "Clay Loam"
      ],
      [
        "Rulindo-Sector-5",
        -2.0860271164823465,
        30.67298350843123,
        "Clay Loam"
      ],
      [
        "Rulindo-Sector-6",
        -2.65357219484458,
        28.978159199578904,
        "Sandy Loam"
      ],
      [
        "Rulindo-Sector-7",
        -1.7536502489917918,
        30.612590896176908,
        "Loam"
      ],
      [
        "Rulindo-Sector-8",
        -1.3369607789364952,
        30.7892220125061,
        "Clay"
      ],
      [
        "Rulindo-Sector-9",
        -1.734600270121688,
        29.53545831807066,
        "Silty Clay"
      ]
    ]
  },
  "Huye": {
    "sectors": [
      [
        "Huye-Sector-1",
        -2.4641738940051354,
        30.674373896828953,
        "Sandy Loam"
      ],
      [
        "Huye-Sector-2",
        -2.216178962190507,
        29.056384704871416,
        "Clay"
      ],
      [
        "Huye-Sector-3",
        -2.227593745050645,
        29.03110904150812,
        "Clay"
      ],
      [
        "Huye-Sector-4",
        -1.6341577830255478,
        28.801092791690163,
        "Sandy Clay"
      ],
      [
        "Huye-Sector-5",
        -1.2506849501385817,
        28.8145994741155,
        "Volcanic Soil"
      ],
      [
        "Huye-Sector-6",
        -1.8386390451242045,
        29.818142939853864,
        "Clay"
      ],
      [
        "Huye-Sector-7",
        -2.584242338799371,
        29.508991859947617,
        "Loamy Sand"
      ],
      [
        "Huye-Sector-8",
        -2.497076124088725,
        29.259404861103448,
        "Volcanic Soil"
      ]
    ]
  },
  "Nyanza": {
    "sectors": [
      [
        "Nyanza-Sector-1",
        -2.7184527824103197,
        29.58668649071559,
        "Clay Loam"
      ],
      [
        "Nyanza-Sector-2",
        -1.1198146454569307,
        29.852183756222043,
        "Volcanic Soil"
      ],
      [
        "Nyanza-Sector-3",
        -1.6143514630858988,
        29.142162296871003,
        "Volcanic Soil"
      ],
      [
        "Nyanza-Sector-4",
        -1.1009951117906371,
        30.782928353962852,
        "Silty Clay"
      ],
      [
        "Nyanza-Sector-5",
        -1.7456039537077659,
        30.77448350699241,
        "Volcanic Soil"
      ],
      [
        "Nyanza-Sector-6",
        -1.5810969837106328,
        30.00407078751106,
        "Clay"
      ],
      [
        "Nyanza-Sector-7",
        -1.97514479711527,
        29.945795257563464,
        "Sandy Clay"
      ],
      [
        "Nyanza-Sector-8",
        -1.6733085938171688,
        30.52289637191966,
        "Volcanic Soil"
      ]
    ]
  },
  "Gisagara": {
    "sectors": [
      [
        "Gisagara-Sector-1",
        -1.271955116321049,
        30.315631994446232,
        "Loamy Sand"
      ],
      [
        "Gisagara-Sector-2",
        -1.4122590760817901,
        29.83697075236522,
        "Clay"
      ],
      [
        "Gisagara-Sector-3",
        -1.5208067985655827,
        29.032870723704846,
        "Silty Clay"
      ],
      [
        "Gisagara-Sector-4",
        -2.605795431412052,
        28.866001289942144,
        "Loamy Sand"
      ],
      [
        "Gisagara-Sector-5",
        -1.9443335982721988,
        29.982878701150405,
        "Silty Clay"
      ],
      [
        "Gisagara-Sector-6",
        -1.1663803469330325,
        29.32351368121264,
        "Sandy Clay"
      ],
      [
        "Gisagara-Sector-7",
        -1.8282860356569883,
        29.226428571943018,
        "Sandy Clay"
      ],
      [
        "Gisagara-Sector-8",
        -2.6614361623081724,
        29.408478051118912,
        "Loam"
      ],
      [
        "Gisagara-Sector-9",
        -1.2151578897725361,
        30.111143501080964,
        "Loam"
      ],
      [
        "Gisagara-Sector-10",
        -1.6598732382812378,
        30.630067239394204,
        "Silty Clay"
      ]
    ]
  },
  "Nyaruguru": {
    "sectors": [
      [
        "Nyaruguru-Sector-1",
        -2.427968152221858,
        29.37531836737438,
        "Silty Clay"
      ],
      [
        "Nyaruguru-Sector-2",
        -2.6185995975206318,
        28.838265833868256,
        "Sandy Loam"
      ],
      [
        "Nyaruguru-Sector-3",
        -1.6871430081917929,
        29.506763851266324,
        "Clay Loam"
      ],
      [
        "Nyaruguru-Sector-4",
        -2.2258438654712296,
        30.574238153035854,
        "Clay Loam"
      ],
      [
        "Nyaruguru-Sector-5",
        -2.186875774964368,
        29.347458509295397,
        "Loamy Sand"
      ],
      [
        "Nyaruguru-Sector-6",
        -2.5873033102810186,
        30.263148047264714,
        "Sandy Clay"
      ]
    ]
  },
  "Nyamagabe": {
    "sectors": [
      [
        "Nyamagabe-Sector-1",
        -1.5607001786223405,
        28.922206550567733,
        "Clay Loam"
      ],
      [
        "Nyamagabe-Sector-2",
        -2.518413323192045,
        29.325510086145652,
        "Loam"
      ],
      [
        "Nyamagabe-Sector-3",
        -2.6310280778536748,
        29.184018593925344,
        "Sandy Clay"
      ],
      [
        "Nyamagabe-Sector-4",
        -2.2961189854973028,
        30.805217089392706,
        "Loamy Sand"
      ],
      [
        "Nyamagabe-Sector-5",
        -1.6171996086996996,
        29.71491308722357,
        "Sandy Clay"
      ]
    ]
  },
  "Ruhango": {
    "sectors": [
      [
        "Ruhango-Sector-1",
        -1.17540476797678,
        29.8610299821405,
        "Volcanic Soil"
      ],
      [
        "Ruhango-Sector-2",
        -2.098687444805434,
        29.42503386646955,
        "Sandy Loam"
      ],
      [
        "Ruhango-Sector-3",
        -2.099436978278506,
        28.822759068108628,
        "Clay"
      ],
      [
        "Ruhango-Sector-4",
        -1.2751423406279383,
        29.545300899971714,
        "Silty Clay"
      ],
      [
        "Ruhango-Sector-5",
        -1.0898884593085512,
        30.796275008568866,
        "Sandy Loam"
      ],
      [
        "Ruhango-Sector-6",
        -1.912553816010751,
        28.974897263510044,
        "Sandy Clay"
      ],
      [
        "Ruhango-Sector-7",
        -2.2722206109434837,
        29.490195545276823,
        "Sandy Loam"
      ],
      [
        "Ruhango-Sector-8",
        -2.4170897889563876,
        30.78700854005155,
        "Volcanic Soil"
      ],
      [
        "Ruhango-Sector-9",
        -1.378687342969803,
        28.991532816402252,
        "Clay Loam"
      ],
      [
        "Ruhango-Sector-10",
        -1.0463532246380616,
        30.89145560826369,
        "Clay Loam"
      ]
    ]
  },
  "Muhanga": {
    "sectors": [
      [
        "Muhanga-Sector-1",
        -2.2980315653340724,
        30.270751442942817,
        "Volcanic Soil"
      ],
      [
        "Muhanga-Sector-2",
        -1.1852015320853613,
        30.662881490956746,
        "Volcanic Soil"
      ],
      [
        "Muhanga-Sector-3",
        -1.2020138222302723,
        30.586949742411775,
        "Clay"
      ],
      [
        "Muhanga-Sector-4",
        -2.5090683146296953,
        30.686963795906866,
        "Silty Clay"
      ],
      [
        "Muhanga-Sector-5",
        -1.7547640814143814,
        29.58179380977966,
        "Clay"
      ]
    ]
  },
  "Kamonyi": {
    "sectors": [
      [
        "Kamonyi-Sector-1",
        -2.0730948920955266,
        28.936273718928863,
        "Clay Loam"
      ],
      [
        "Kamonyi-Sector-2",
        -1.0675948691041999,
        29.328742821233266,
        "Clay Loam"
      ],
      [
        "Kamonyi-Sector-3",
        -1.5179129381360044,
        29.11098255290214,
        "Volcanic Soil"
      ],
      [
        "Kamonyi-Sector-4",
        -2.733603494761841,
        30.08008510135778,
        "Clay Loam"
      ],
      [
        "Kamonyi-Sector-5",
        -2.0601333760271836,
        28.869406539091152,
        "Volcanic Soil"
      ]
    ]
  },
  "Karongi": {
    "sectors": [
      [
        "Karongi-Sector-1",
        -1.6581675795375452,
        30.22948144826501,
        "Sandy Clay"
      ],
      [
        "Karongi-Sector-2",
        -1.9189850315003865,
        30.86986595363226,
        "Volcanic Soil"
      ],
      [
        "Karongi-Sector-3",
        -1.7331458970170917,
        28.969791985298702,
        "Volcanic Soil"
      ],
      [
        "Karongi-Sector-4",
        -2.3722524208136804,
        30.329254332084904,
        "Volcanic Soil"
      ],
      [
        "Karongi-Sector-5",
        -1.9534588579971306,
        30.865188595879168,
        "Loam"
      ]
    ]
  },
  "Rubavu": {
    "sectors": [
      [
        "Rubavu-Sector-1",
        -1.2205503756513048,
        30.34364919198816,
        "Sandy Clay"
      ],
      [
        "Rubavu-Sector-2",
        -1.0583550072635546,
        29.950740954820983,
        "Sandy Clay"
      ],
      [
        "Rubavu-Sector-3",
        -1.448893447046455,
        30.494352952461252,
        "Clay"
      ],
      [
        "Rubavu-Sector-4",
        -1.4830340404606475,
        29.06814843178718,
        "Clay"
      ],
      [
        "Rubavu-Sector-5",
        -1.4024566706644057,
        29.515687434531337,
        "Loam"
      ],
      [
        "Rubavu-Sector-6",
        -1.7886399541412075,
        29.301053405559713,
        "Loamy Sand"
      ],
      [
        "Rubavu-Sector-7",
        -1.4484320779753046,
        30.38454003557783,
        "Clay"
      ]
    ]
  },
  "Rusizi": {
    "sectors": [
      [
        "Rusizi-Sector-1",
        -1.4011355513306138,
        29.97264892444519,
        "Sandy Loam"
      ],
      [
        "Rusizi-Sector-2",
        -2.3522965220254815,
        29.493530310940105,
        "Loam"
      ],
      [
        "Rusizi-Sector-3",
        -1.9132748122764536,
        28.82384265401158,
        "Silty Clay"
      ],
      [
        "Rusizi-Sector-4",
        -1.7713485546309808,
        30.3560451079124,
        "Volcanic Soil"
      ],
      [
        "Rusizi-Sector-5",
        -2.588452755801211,
        30.163341634443732,
        "Clay"
      ],
      [
        "Rusizi-Sector-6",
        -1.5741290312255638,
        29.298763589714188,
        "Clay"
      ],
      [
        "Rusizi-Sector-7",
        -2.1252329568573325,
        29.399995381191907,
        "Volcanic Soil"
      ]
    ]
  },
  "Nyamasheke": {
    "sectors": [
      [
        "Nyamasheke-Sector-1",
        -2.3540842188979165,
        29.54754262516765,
        "Sandy Clay"
      ],
      [
        "Nyamasheke-Sector-2",
        -2.583703633949844,
        29.517947300104442,
        "Silty Clay"
      ],
      [
        "Nyamasheke-Sector-3",
        -2.7171952443608447,
        28.88553048486984,
        "Loam"
      ],
      [
        "Nyamasheke-Sector-4",
        -1.0368810484812845,
        29.168193566767613,
        "Volcanic Soil"
      ],
      [
        "Nyamasheke-Sector-5",
        -2.623898510828197,
        29.832393337745348,
        "Loamy Sand"
      ],
      [
        "Nyamasheke-Sector-6",
        -2.1766522220390785,
        29.775815007173183,
        "Sandy Clay"
      ],
      [
        "Nyamasheke-Sector-7",
        -2.082691478084728,
        30.093285205909655,
        "Sandy Clay"
      ]
    ]
  },
  "Nyabihu": {
    "sectors": [
      [
        "Nyabihu-Sector-1",
        -1.879583682050312,
        29.85318421884312,
        "Sandy Clay"
      ],
      [
        "Nyabihu-Sector-2",
        -2.4503068836783237,
        28.94897592569985,
        "Loam"
      ],
      [
        "Nyabihu-Sector-3",
        -1.367573195015018,
        30.669011217816887,
        "Loamy Sand"
      ],
      [
        "Nyabihu-Sector-4",
        -2.7502898106273315,
        30.015616280565872,
        "Volcanic Soil"
      ],
      [
        "Nyabihu-Sector-5",
        -1.7590957462068868,
        28.87547877497316,
        "Clay"
      ],
      [
        "Nyabihu-Sector-6",
        -2.5209250898900604,
        30.861865865452113,
        "Loam"
      ],
      [
        "Nyabihu-Sector-7",
        -1.7365001309757806,
        28.864050524872006,
        "Silty Clay"
      ],
      [
        "Nyabihu-Sector-8",
        -2.730097478027038,
        29.43685758081377,
        "Sandy Loam"
      ]
    ]
  },
  "Ngororero": {
    "sectors": [
      [
        "Ngororero-Sector-1",
        -2.1068240885165346,
        30.5873870101854,
        "Volcanic Soil"
      ],
      [
        "Ngororero-Sector-2",
        -1.9264962263026315,
        29.582642420897503,
        "Clay Loam"
      ],
      [
        "Ngororero-Sector-3",
        -1.1149214065105943,
        30.261662573017443,
        "Volcanic Soil"
      ],
      [
        "Ngororero-Sector-4",
        -2.673250964470821,
        29.238729306992255,
        "Loamy Sand"
      ],
      [
        "Ngororero-Sector-5",
        -1.0179030698123261,
        29.0941764319967,
        "Sandy Loam"
      ],
      [
        "Ngororero-Sector-6",
        -2.2684769408459102,
        29.47735660490106,
        "Volcanic Soil"
      ],
      [
        "Ngororero-Sector-7",
        -1.5453716662085175,
        30.27521657637293,
        "Volcanic Soil"
      ],
      [
        "Ngororero-Sector-8",
        -1.8049240415657661,
        29.422671301660376,
        "Clay Loam"
      ],
      [
        "Ngororero-Sector-9",
        -1.3417958895774746,
        30.620851869018217,
        "Sandy Clay"
      ]
    ]
  },
  "Rutsiro": {
    "sectors": [
      [
        "Rutsiro-Sector-1",
        -2.3975274906649853,
        30.822767332825283,
        "Silty Clay"
      ],
      [
        "Rutsiro-Sector-2",
        -1.0397787962423124,
        29.967610581149426,
        "Loamy Sand"
      ],
      [
        "Rutsiro-Sector-3",
        -1.195942395343472,
        29.90817232908123,
        "Sandy Loam"
      ],
      [
        "Rutsiro-Sector-4",
        -1.145591712498413,
        29.331279352777408,
        "Sandy Loam"
      ],
      [
        "Rutsiro-Sector-5",
        -1.0552554358856219,
        29.89850547275731,
        "Clay"
      ]
    ]
  }
}